src/__init__.py
src/cli.py
lepoa-1.0.0.dist-info/METADATA
lepoa-1.0.0.dist-info/WHEEL
lepoa-1.0.0.dist-info/entry_points.txt
lepoa-1.0.0.dist-info/top_level.txt
lepoa-1.0.0.dist-info/RECORD
