Metadata-Version: 2.1
Name: lepoa
Version: 1.0.0
Summary: Un generador de lenguajes de programación transpilados.
Author: Hernandez Barreto Alan Daleth
Author-email: alandaleth.hb@gmail.com
Requires-Dist: argparse
